pytest_django_sqlcount.py
pytest_django_sqlcounts-0.1.0.dist-info/RECORD
pytest_django_sqlcounts-0.1.0.dist-info/top_level.txt
pytest_django_sqlcounts-0.1.0.dist-info/DESCRIPTION.rst
pytest_django_sqlcounts-0.1.0.dist-info/METADATA
pytest_django_sqlcounts-0.1.0.dist-info/metadata.json
pytest_django_sqlcounts-0.1.0.dist-info/entry_points.txt
pytest_django_sqlcounts-0.1.0.dist-info/WHEEL
