Metadata-Version: 2.0
Name: pytest-django-sqlcounts
Version: 0.1.0
Summary: py.test plugin for reporting the number of SQLs executed per django testcase.
Home-page: https://github.com/stj/pytest-django-sqlcount
Author: Stefan Tjarks
Author-email: stefan [at] tjarks [dot] de
License: MIT License
Keywords: py.test pytest django sqlcount
Platform: UNKNOWN
Classifier: Development Status :: 4 - Beta
Classifier: Intended Audience :: Developers
Classifier: License :: OSI Approved :: MIT License
Classifier: Operating System :: OS Independent
Classifier: Programming Language :: Python
Classifier: Programming Language :: Python :: 2.7
Classifier: Topic :: Software Development :: Testing
Requires-Dist: py (>=1.4.22)
Requires-Dist: pytest (>=2.6.0)
Requires-Dist: pytest-django (>=2.7.0)
